dsr_data_tools/__init__.py
dsr_data_tools/analysis.py
dsr_data_tools/enums.py
dsr_data_tools/recommendations.py
dsr_data_tools-0.0.6.dist-info/licenses/LICENSE
dsr_data_tools-0.0.6.dist-info/METADATA
dsr_data_tools-0.0.6.dist-info/WHEEL
dsr_data_tools-0.0.6.dist-info/top_level.txt
dsr_data_tools-0.0.6.dist-info/RECORD
